{"name": "Россия_югары_уку_йортларын_тәмамлаучылар", "id": 185725, "predecessors": [{"name": "Россия", "id": 24324}, {"name": "Югары_уку_йортларын_тәмамлаучылар", "id": 162953}], "successors": [{"name": "Уфа_сәнгать_институтын_тәмамлаучылар", "id": 162948}, {"name": "ВГИК_тәмамлаучылар", "id": 163243}, {"name": "МХАТ_мәктәп-студиясен_тәмамлаучылар", "id": 163376}, {"name": "Санкт-Петербург_сәнгать_академиясен_тәмамлаучылар", "id": 163872}, {"name": "Санкт-Петербург_консерваториясен_тәмамлаучылар", "id": 164030}, {"name": "Гнесиннар_исемендәге_академияне_тәмамлаучылар", "id": 164510}, {"name": "Щукин_исемендәге_театр_укуханәсен_тәмамлаучылар", "id": 166347}, {"name": "Щепкин_театр_укуханәсен_тәмамлаучылар", "id": 167049}, {"name": "Казан_дәүләт_мәдәният_һәм_сәнгать_университетын_тәмамлаучылар", "id": 168866}, {"name": "Мәскәү_дәүләт_мәдәният_институтын_тәмамлаучылар", "id": 169813}, {"name": "Суриков_исемендәге_рәсем_институтын_тәмамлаучылар", "id": 174325}, {"name": "Санкт-Петербург_дәүләт_театр_сәнгате_академиясен_тәмамлаучылар", "id": 175410}, {"name": "Строганов_исемендәге_Мәскәү_сәнгать-сәнәгать_академиясен_тәмамлаучылар", "id": 179956}, {"name": "Император_сәнгать_академиясен_тәмамлаучылар", "id": 184355}, {"name": "Мәскәү_юридик_институтын_тәмамлаучылар", "id": 176020}, {"name": "Казан_юридик_институтын_тәмамлаучылар", "id": 227780}, {"name": "Мәскәү_вузларын_тәмамлаучылар", "id": 171448}, {"name": "Казан_югары_уку_йортларын_тәмамлаучылар", "id": 185722}, {"name": "Горький_политехника_институтын_тәмамлаучылар", "id": 163320}, {"name": "Ленинград_физик_тәрбия_институтын_тәмамлаучылар", "id": 166647}, {"name": "Ленинград_зооветеринария_институтын_тәмамлаучылар", "id": 168678}, {"name": "Ленинград_элемтә_электротехника_институтын_тәмамлаучылар", "id": 171815}, {"name": "Ленинград_көнчыгыш_педагогика_институтын_тәмамлаучылар", "id": 171879}, {"name": "Санкт-Петербург_дәүләт_университетын_тәмамлаучылар", "id": 172275}, {"name": "Репин_исемендәге_институтны_тәмамлаучылар", "id": 176306}, {"name": "Санкт-Петербург_хәрби-медицина_академиясен_тәмамлаучылар", "id": 178477}, {"name": "Россия_дәүләт_педагогика_университетын_тәмамлаучылар", "id": 185898}, {"name": "Санкт-Петербург_мәдәният_һәм_сәнгать_университетын_тәмамлаучылар", "id": 187699}, {"name": "Санкт-Петербург_руханилар_академиясен_тәмамлаучылар", "id": 198735}, {"name": "Матди-техник_тәэмин_итү_хәрби_академиясен_тәмамлаучылар", "id": 202568}, {"name": "Фрунзе_исемендәге_хәрби-диңгез_укуханәсен_тәмамлаучылар", "id": 204935}, {"name": "Төньяк-Көнбатыш_идарә_институтын_тәмамлаучылар", "id": 227753}, {"name": "Санкт-Петербург_гражданнар_авиациясе_университетын_тәмамлаучылар", "id": 583971}, {"name": "Н._К._Рерих_исемендәге_Санкт-Петербург_сәнгать_училищесын_тәмамлаучылар", "id": 662217}, {"name": "Чиләбе_дәүләт_мәдәният_институтын_тәмамлаучылар", "id": 210798}, {"name": "Чиләбе_дәүләт_педагогика_университетын_тәмамлаучылар", "id": 217821}, {"name": "Ырынбур_педагогия_институтын_тәмамлаучылар", "id": 219005}, {"name": "Төмән_дәүләт_университетын_тәмамлаучылар", "id": 235835}, {"name": "В._И._Ленин_исемендәге_Сембер_югары_хәрби_танк_команда_училищесын_тәмамлаучылар", "id": 246918}, {"name": "И._Н._Ульянов_исемендәге_Сембер_ДПУ_тәмамлаучылар", "id": 247040}, {"name": "Якутск_дәүләт_университетын_тәмамлаучылар", "id": 427987}]}