{"name": "Независна_Држава_Хрватска", "id": 81719, "predecessors": [{"name": "Бивше_државе_на_Балканском_полуострву", "id": 199393}, {"name": "Босна_и_Херцеговина_у_Другом_светском_рату", "id": 456977}, {"name": "Државе_и_територије_под_контролом_Сила_осовине", "id": 641037}, {"name": "Србија_у_Другом_светском_рату", "id": 78697}, {"name": "Холокауст_у_Југославији", "id": 4334126}, {"name": "Хрватска_у_Другом_светском_рату", "id": 569374}, {"name": "Хрватски_иредентизам", "id": 4355880}, {"name": "Хрватски_национализам", "id": 4332440}], "successors": [{"name": "Усташе", "id": 81012}, {"name": "Концентрациони_логори_у_НДХ", "id": 83726}, {"name": "Напади_на_гарнизоне_НДХ", "id": 143821}, {"name": "Министри_Владе_НДХ", "id": 697733}, {"name": "Филмови_на_тему_геноцида_над_Србима_у_НДХ", "id": 4384649}, {"name": "Битка_на_Неретви", "id": 451438}]}