{"name": "Svenska_sångare_inom_populärmusik", "id": 209890, "predecessors": [{"name": "Svenska_musiker_inom_populärmusik", "id": 209884}, {"name": "Svenska_sångare", "id": 123331}, {"name": "Sångare_inom_populärmusik", "id": 210169}], "successors": [{"name": "Svenska_rappare", "id": 207438}, {"name": "Svenska_jazzsångare", "id": 207496}, {"name": "Svenska_dansbandssångare", "id": 207499}, {"name": "Svenska_musikalartister", "id": 207874}, {"name": "Svenska_countrysångare", "id": 378090}, {"name": "Svenska_popsångare", "id": 492500}, {"name": "Svenska_rocksångare", "id": 492501}, {"name": "Svenska_vispopartister", "id": 522669}, {"name": "Svenska_soulsångare", "id": 874779}, {"name": "Svenska_schlagersångare", "id": 1371584}, {"name": "Svenska_gospelsångare", "id": 1371587}, {"name": "Svenska_discosångare", "id": 1371588}, {"name": "Svenska_bluessångare", "id": 1371727}, {"name": "Svenska_punksångare", "id": 1371966}, {"name": "Svenska_metalsångare", "id": 1489310}, {"name": "Svenska_R&B-sångare", "id": 1661097}, {"name": "Svenska_danspopsångare", "id": 1677918}, {"name": "Svenska_indiepopsångare", "id": 3912247}]}