{"name": "VVS", "id": 72046, "predecessors": [{"name": "Byggteknik", "id": 142761}, {"name": "Energiteknik", "id": 117552}, {"name": "Fastighetsförvaltning", "id": 3922010}, {"name": "Hygien", "id": 118729}, {"name": "Infrastruktur", "id": 61487}, {"name": "Vatten", "id": 222479}], "successors": [{"name": "Toaletter", "id": 510937}, {"name": "Uppvärmning", "id": 542235}, {"name": "Pumpar", "id": 624762}, {"name": "Avlopp", "id": 709013}, {"name": "Vattenförsörjning", "id": 741900}, {"name": "Ventiler", "id": 865264}, {"name": "Bevattning", "id": 955305}, {"name": "Tvagning", "id": 3440249}, {"name": "Dagvatten", "id": 3907644}]}