{"name": "War_and_politics", "id": 25687593, "predecessors": [{"name": "Psychological_warfare", "id": 1312487}, {"name": "War", "id": 691877}], "successors": [{"name": "Anti-war_movement", "id": 1854571}, {"name": "Politics_of_the_American_Civil_War", "id": 7183258}, {"name": "Politics_of_World_War_II", "id": 17868255}, {"name": "Politics_of_World_War_I", "id": 36771691}, {"name": "Politics_of_the_Nepalese_Civil_War", "id": 66766232}, {"name": "Politics_of_the_Iraq_War", "id": 75620279}, {"name": "Politics_of_the_Kashmir_conflict", "id": 76228036}, {"name": "Politics_of_the_Arab–Israeli_conflict", "id": 76397971}, {"name": "World_War_II_propaganda", "id": 30299758}, {"name": "World_War_I_propaganda", "id": 36441476}, {"name": "Propaganda_in_the_Iraq_War", "id": 75658694}, {"name": "Politicians_of_the_Tigray_War", "id": 75530885}]}