{"name": "Asian_women's_national_association_football_teams", "id": 43444661, "predecessors": [{"name": "Asian_national_association_football_teams", "id": 27217184}, {"name": "Women's_sports_organizations", "id": 15707669}, {"name": "Athletic_sports", "id": 31210709}], "successors": [{"name": "Asian_women's_national_futsal_teams", "id": 52755454}, {"name": "Asian_women's_national_under-20_association_football_teams", "id": 71871900}, {"name": "Asian_women's_national_under-17_association_football_teams", "id": 71871970}, {"name": "South_Korea_women's_international_footballers", "id": 46238341}, {"name": "Japan_women's_international_footballers", "id": 15981022}, {"name": "Japan_women's_national_football_team_managers", "id": 34922434}, {"name": "Japan_women's_national_football_team_results", "id": 56917835}, {"name": "China_women's_national_football_team_managers", "id": 34922585}, {"name": "China_women's_international_footballers", "id": 47003049}, {"name": "Australia_women's_international_soccer_players", "id": 43200128}, {"name": "Australia_women's_national_soccer_team_managers", "id": 44980965}, {"name": "Chinese_Taipei_women's_international_footballers", "id": 46999397}, {"name": "North_Korea_women's_international_footballers", "id": 53290982}, {"name": "Lebanon_women's_international_footballers", "id": 61676468}, {"name": "Iran_women's_international_footballers", "id": 53862086}, {"name": "Nepal_women's_international_footballers", "id": 44309366}, {"name": "India_women's_international_footballers", "id": 43828647}, {"name": "Jordan_women's_international_footballers", "id": 47240906}, {"name": "Philippines_women's_international_footballers", "id": 45290889}, {"name": "Philippines_women's_national_football_team_managers", "id": 51846536}, {"name": "Thailand_women's_international_footballers", "id": 52050756}, {"name": "Myanmar_women's_international_footballers", "id": 47232416}, {"name": "Vietnam_women's_international_footballers", "id": 52168813}, {"name": "United_Arab_Emirates_women's_international_footballers", "id": 65348069}]}