{"name": "Yemeni_crisis", "id": 45341448, "predecessors": [{"name": "2010s_conflicts", "id": 29164287}, {"name": "2010s_in_Yemen", "id": 27769226}, {"name": "2020s_conflicts", "id": 62786810}, {"name": "2020s_in_Yemen", "id": 62786831}, {"name": "Shia–Sunni_sectarian_violence", "id": 38725232}, {"name": "Modern_history_by_country", "id": 15379408}, {"name": "Politics_of_Yemen", "id": 2860989}, {"name": "History_of_the_Middle_East", "id": 895924}], "successors": [{"name": "Yemeni_revolution", "id": 41111520}, {"name": "Houthi_insurgency", "id": 45326844}, {"name": "Yemeni_civil_war_(2014–present)", "id": 46395042}, {"name": "Organizations_of_the_Yemeni_Crisis_(2011–present)", "id": 52229082}, {"name": "Yemeni_humanitarian_crisis", "id": 75681516}]}