{"name": "Depictions_of_women_in_film", "id": 60279464, "predecessors": [{"name": "Cultural_depictions_of_women", "id": 36597074}, {"name": "Women_in_film", "id": 29809554}], "successors": [{"name": "Lesbian-related_films", "id": 9700830}, {"name": "Portrayals_of_Mary,_mother_of_Jesus,_in_film", "id": 29777881}, {"name": "Films_based_on_Little_Red_Riding_Hood", "id": 37251662}, {"name": "Female_characters_in_film", "id": 53872215}, {"name": "Films_about_misogyny", "id": 56585050}, {"name": "Portrayals_of_Mary_Magdalene_in_film", "id": 63882858}, {"name": "Psycho-biddy_films", "id": 65483402}, {"name": "Films_about_father–daughter_relationships", "id": 65855014}, {"name": "Succubi_in_film", "id": 65937921}, {"name": "Miss_Prissy_films", "id": 75634369}, {"name": "Granny_(Looney_Tunes)_films", "id": 76130366}, {"name": "Films_about_uxoricide", "id": 76731461}, {"name": "Documentary_films_about_feminism", "id": 32051718}, {"name": "Feminism_in_anime_and_manga", "id": 57248602}, {"name": "Films_about_abortion", "id": 32756888}, {"name": "Teenage_pregnancy_in_film", "id": 38632908}, {"name": "Films_about_surrogacy", "id": 56073940}, {"name": "2010s_feminist_films", "id": 60799849}, {"name": "2000s_feminist_films", "id": 60806585}, {"name": "1990s_feminist_films", "id": 60839392}, {"name": "1980s_feminist_films", "id": 60849549}, {"name": "1970s_feminist_films", "id": 60973184}, {"name": "1950s_feminist_films", "id": 60973259}, {"name": "1960s_feminist_films", "id": 60973505}, {"name": "2020s_feminist_films", "id": 61299862}, {"name": "Animated_films_about_mother–daughter_relationships", "id": 75136681}, {"name": "Animated_films_about_mother–son_relationships", "id": 75136738}]}