{"name": "Ideologies", "id": 6822085, "predecessors": [{"name": "Belief", "id": 956054}, {"name": "Thought", "id": 983652}], "successors": [{"name": "Transhumanism", "id": 840164}, {"name": "Economic_ideologies", "id": 3050197}, {"name": "Ideological_rivalry", "id": 5501844}, {"name": "Political_ideologies", "id": 6243762}, {"name": "Feminist_movements_and_ideologies", "id": 38617283}, {"name": "State_ideologies", "id": 54627662}, {"name": "Technological_utopianism", "id": 63174556}, {"name": "Totalitarian_ideologies", "id": 75566200}, {"name": "Books_about_ideologies", "id": 12138755}, {"name": "Works_about_postmodernism", "id": 35072472}, {"name": "Anti-fascist_works", "id": 35426975}, {"name": "Works_about_antisemitism", "id": 35464166}, {"name": "Works_about_Stalinism", "id": 35521354}, {"name": "Works_about_totalitarianism", "id": 36470664}, {"name": "Works_about_Objectivism_(Ayn_Rand)", "id": 37644247}, {"name": "Works_about_capitalism", "id": 39544667}, {"name": "Works_about_nihilism", "id": 41316999}, {"name": "Works_about_Islamic_terrorism", "id": 45254001}, {"name": "Works_about_existentialism", "id": 45383366}, {"name": "Works_about_philosophical_pessimism", "id": 63806526}, {"name": "Works_about_utilitarianism", "id": 63936666}, {"name": "Anti-communist_works", "id": 71060984}, {"name": "Feminist_journals", "id": 37661964}, {"name": "Terrorism", "id": 701590}, {"name": "Religious_fanaticism", "id": 53727259}, {"name": "Radicalization", "id": 67067694}, {"name": "History_of_socialism", "id": 3741008}, {"name": "History_of_anarchism", "id": 4001674}, {"name": "History_of_libertarianism", "id": 20212659}, {"name": "History_of_Zionism", "id": 29401635}, {"name": "History_of_liberalism", "id": 69121069}, {"name": "Historians_of_anarchism", "id": 5863375}, {"name": "Historians_of_communism", "id": 13336051}, {"name": "Historians_of_fascism", "id": 31130926}, {"name": "Historians_of_Nazism", "id": 31130953}, {"name": "Feminism", "id": 701235}, {"name": "Nationalism", "id": 846456}, {"name": "Utopian_socialism", "id": 1118253}, {"name": "Eugenics", "id": 1270749}, {"name": "Anti-racism", "id": 6074933}, {"name": "African_and_Black_nationalism", "id": 7356235}, {"name": "Anti-intellectualism", "id": 8862983}, {"name": "Multiculturalism", "id": 11586618}, {"name": "Natalism", "id": 22497740}, {"name": "Neo-Confucianism", "id": 22975025}, {"name": "Individualism", "id": 24193500}, {"name": "Collectivism", "id": 33502265}, {"name": "Masculism", "id": 40129278}, {"name": "Cosmopolitanism", "id": 46538243}, {"name": "Social_conservatism", "id": 60682902}, {"name": "Owenism", "id": 69870903}, {"name": "Accelerationism", "id": 70914176}, {"name": "Television_episodes_about_antisemitism", "id": 62544290}, {"name": "Television_episodes_about_racism", "id": 62556675}, {"name": "Counterterrorism", "id": 3223549}, {"name": "Islamic_theology", "id": 14136404}]}