{"name": "Northern_Europe", "id": 709704, "predecessors": [{"name": "Regions_of_Europe", "id": 1023050}], "successors": [{"name": "Nordic_countries", "id": 696969}, {"name": "Scandinavia", "id": 696971}, {"name": "Hanseatic_League", "id": 3470665}, {"name": "Flora_of_Northern_Europe", "id": 42948570}, {"name": "Archaeology_of_Northern_Europe", "id": 55516923}, {"name": "Lichens_of_Northern_Europe", "id": 71280458}, {"name": "British_Isles", "id": 724452}, {"name": "Channel_Islands", "id": 1071519}, {"name": "Benelux", "id": 33481662}, {"name": "Capital_Region_of_Denmark", "id": 24744749}, {"name": "Geography_of_the_Øresund_Region", "id": 73664604}, {"name": "Protected_areas_in_the_Øresund_Region", "id": 73864864}, {"name": "People_from_Malmö_Municipality", "id": 23607969}, {"name": "People_from_Helsingborg_Municipality", "id": 23608016}, {"name": "People_from_Lund_Municipality", "id": 23636928}, {"name": "People_from_Landskrona_Municipality", "id": 23700696}, {"name": "People_from_Kävlinge_Municipality", "id": 23871933}, {"name": "People_from_Vellinge_Municipality", "id": 27004314}, {"name": "People_from_Svalöv_Municipality", "id": 27035721}]}