{"name": "Massacres_in_Russia", "id": 8501839, "predecessors": [{"name": "Human_rights_abuses_in_Russia", "id": 45450497}, {"name": "History_of_Asia", "id": 3515536}, {"name": "History_of_Russia", "id": 2169965}], "successors": [{"name": "Katyn_massacre", "id": 29725556}, {"name": "1993_Russian_constitutional_crisis", "id": 55212594}, {"name": "Massacres_of_the_Russian_Civil_War", "id": 75652976}, {"name": "Massacres_in_the_Chechen–Russian_conflict", "id": 75897131}, {"name": "Anti-Jewish_pogroms_in_the_Russian_Empire", "id": 26111178}]}