{"name": "Sinh_thế_kỷ_12", "id": 19355, "predecessors": [{"name": "Thế_kỷ_12", "id": 49327}, {"name": "Thế_kỷ_13", "id": 49328}], "successors": [{"name": "Sinh_năm_1200", "id": 20792}, {"name": "Sinh_thập_niên_1100", "id": 53636}, {"name": "Sinh_thập_niên_1120", "id": 53640}, {"name": "Sinh_thập_niên_1130", "id": 53642}, {"name": "Sinh_thập_niên_1140", "id": 53644}, {"name": "Sinh_thập_niên_1150", "id": 53646}, {"name": "Sinh_thập_niên_1160", "id": 53648}, {"name": "Sinh_thập_niên_1170", "id": 53650}, {"name": "Sinh_thập_niên_1180", "id": 53652}, {"name": "Sinh_thập_niên_1190", "id": 53654}, {"name": "Sinh_năm_1113", "id": 20520}, {"name": "Sinh_năm_1118", "id": 20538}]}