{"name": "Historia_de_Israel", "id": 134729, "predecessors": [{"name": "Historia_de_los_judíos", "id": 532851}, {"name": "Israel", "id": 65827}, {"name": "Historia_de_Asia", "id": 51465}, {"name": "Historia", "id": 50578}, {"name": "Historia_de_Oriente_Medio", "id": 314720}], "successors": [{"name": "Historia_de_Palestina", "id": 178941}, {"name": "Historia_de_la_formación_del_Estado_de_Israel", "id": 919778}, {"name": "Historiadores_de_Israel", "id": 1272772}, {"name": "Masacres_en_Israel", "id": 4990239}, {"name": "Belén", "id": 5556120}, {"name": "Siria_otomana", "id": 9571649}, {"name": "Masacres_cometidas_por_Israel", "id": 10764997}, {"name": "Programa_nuclear_de_Israel", "id": 5699374}, {"name": "Historia_antigua_de_Israel", "id": 919785}, {"name": "Historia_medieval_de_Israel", "id": 8008476}, {"name": "Yacimientos_arqueológicos_de_Israel", "id": 1277297}, {"name": "Resoluciones_del_Consejo_de_Seguridad_de_las_Naciones_Unidas_referentes_a_Israel", "id": 4173676}]}