{"name": "Cultura_de_El_Salvador", "id": 152210, "predecessors": [{"name": "Comunidad_Iberoamericana_de_Naciones", "id": 1360480}, {"name": "Cartografía", "id": 51115}, {"name": "Geografía_física", "id": 741956}, {"name": "América_Central", "id": 51491}, {"name": "Cultura_de_América_Latina", "id": 783975}], "successors": [{"name": "Ciudad_de_Santa_Ana_(El_Salvador)", "id": 949178}, {"name": "Museos_de_El_Salvador", "id": 1128856}, {"name": "Deporte_en_El_Salvador", "id": 4168810}, {"name": "Profesores_de_El_Salvador", "id": 694541}, {"name": "Gastronomía_de_El_Salvador", "id": 150973}, {"name": "Leyendas_de_El_Salvador", "id": 753317}, {"name": "Religiosos_católicos_de_El_Salvador", "id": 10366496}, {"name": "Periódicos_de_El_Salvador", "id": 656638}, {"name": "Televisión_de_El_Salvador", "id": 1774979}, {"name": "Telecorporación_Salvadoreña", "id": 3111788}, {"name": "Médicos_de_El_Salvador", "id": 694604}, {"name": "Elecciones_en_El_Salvador", "id": 2185455}, {"name": "Nuestra_Belleza_El_Salvador", "id": 2528087}, {"name": "Turismo_en_El_Salvador", "id": 1297795}, {"name": "Municipios_de_La_Unión", "id": 844931}, {"name": "Deporte_en_San_Salvador", "id": 4833268}, {"name": "Museos_de_San_Salvador", "id": 6984407}, {"name": "Historiadores_de_El_Salvador", "id": 784228}, {"name": "Municipios_de_Chalatenango", "id": 844951}]}