{"name": "Monedas_de_Asia", "id": 670953, "predecessors": [{"name": "Economía_de_Asia", "id": 165898}, {"name": "Monedas", "id": 52085}], "successors": [{"name": "Euro", "id": 325345}, {"name": "Monedas_de_Rusia", "id": 1030796}, {"name": "Monedas_de_China", "id": 1031653}, {"name": "Monedas_de_Armenia", "id": 1032720}, {"name": "Monedas_de_Azerbaiyán", "id": 1032722}, {"name": "Monedas_de_Georgia", "id": 1032725}, {"name": "Monedas_de_Japón", "id": 1048551}, {"name": "Monedas_de_Israel", "id": 1063040}, {"name": "Monedas_circulantes_de_Asia", "id": 2286723}]}