{"name": "Politik_(Alberta)", "id": 5913819, "predecessors": [{"name": "Politik_(Kanada)", "id": 5706129}, {"name": "!Hauptkategorie", "id": 235489}], "successors": [{"name": "Mitglied_der_Progressive_Conservative_Association_of_Alberta", "id": 9358268}, {"name": "Municipal_District_in_Alberta", "id": 11662483}, {"name": "Premierminister_(Alberta)", "id": 3319394}, {"name": "Vizegouverneur_(Alberta)", "id": 4399414}, {"name": "Abgeordneter_der_Legislativversammlung_von_Alberta", "id": 10261767}]}