{"name": "افراد_اندلس_(اسلامی)", "id": 1815840, "predecessors": [{"name": "اندلس_(اسلامی)", "id": 1323619}, {"name": "اهالی_اندلس", "id": 177827}, {"name": "مسلمانان_اهل_اسپانیا", "id": 3217937}, {"name": "افراد", "id": 112317}, {"name": "اسپانیا_در_قرون_وسطی", "id": 4295329}], "successors": [{"name": "دودمان_نصریان", "id": 1814151}, {"name": "امیرهای_کوردوبا", "id": 2425070}, {"name": "خلفای_اموی_کوردوبا", "id": 2472988}, {"name": "شاعران_اندلس_(اسلامی)", "id": 3619510}, {"name": "والیان_اموی_اندلس", "id": 4304023}, {"name": "دودمان‌های_اندلس", "id": 5744195}, {"name": "امیران_غرناطه", "id": 3621546}]}