{"name": "بازی‌های_ویدئویی_واقع‌شده_در_قرون_وسطی", "id": 2290572, "predecessors": [{"name": "افسانه‌های_واقع‌شده_در_قرون_وسطی", "id": 2289808}, {"name": "بازی‌های_ویدئویی_با_پیش‌زمینه_تاریخی", "id": 4076062}, {"name": "قرون_وسطی", "id": 237490}], "successors": [{"name": "بازی‌های_ویدئویی_واقع‌شده_در_تاریخ_ژاپن", "id": 1553134}, {"name": "بازی‌های_ویدئویی_فانتزی_واقع‌شده_در_قرون_وسطی", "id": 2290539}, {"name": "بازی‌های_ویدئویی_واقع‌شده_در_جنگ‌های_صلیبی", "id": 2290561}, {"name": "بازی‌های_ویدئویی_واقع‌شده_در_انگلستان_قرون_وسطی", "id": 4555519}, {"name": "بازی‌های_ویدئویی_واقع‌شده_در_امپراتوری_روم_شرقی", "id": 4555561}, {"name": "مجموعه_ارباب", "id": 4942695}, {"name": "بازی‌های_ویدئویی_واقع‌شده_در_عصر_وایکینگ‌ها", "id": 5783652}]}