{"name": "جانوران_کرتاسه", "id": 3208771, "predecessors": [{"name": "میانه‌زیستی", "id": 284062}, {"name": "کرتاسه", "id": 281965}], "successors": [{"name": "پرندگان_کرتاسه", "id": 3208755}, {"name": "جانوران_کرتاسه_آسیا", "id": 3619082}, {"name": "جانوران_کرتاسه_آمریکای_شمالی", "id": 3619084}, {"name": "آمونیت‌های_کرتاسه", "id": 5504788}, {"name": "ماهیان_کرتاسه", "id": 3508691}, {"name": "پستان‌داران_کرتاسه", "id": 3508681}, {"name": "خزندگان_کرتاسه", "id": 3513843}, {"name": "دایناسورهای_کرتاسه_پیشین", "id": 3508656}, {"name": "خزندگان_کرتاسه_پیشین_استرالیا", "id": 3619180}, {"name": "خزندگان_کرتاسه_پیشین_آفریقا", "id": 3619182}, {"name": "خزندگان_کرتاسه_پیشین_آمریکای_جنوبی", "id": 3619183}, {"name": "تمساح‌ریختان_کرتاسه_پیشین", "id": 5281092}, {"name": "پستان‌داران_کرتاسه_پیشین_آسیا", "id": 3508673}, {"name": "دایناسورهای_کرتاسه_پسین", "id": 3513826}, {"name": "ماهیان_کرتاسه_پسین", "id": 5282959}, {"name": "بریده‌مهرگان_کرتاسه", "id": 4846911}, {"name": "خزندگان_کرتاسه_پسین_آمریکای_شمالی", "id": 3619179}, {"name": "ماهیان_کرتاسه_پسین_آمریکای_شمالی", "id": 5282963}, {"name": "موساسوریان_آفریقا", "id": 3620035}, {"name": "دایناسورهای_کرتاسه_پسین_آفریقا", "id": 5504746}, {"name": "موساسوریان_اروپا", "id": 3620032}, {"name": "دایناسورهای_کرتاسه_پسین_اروپا", "id": 5504747}, {"name": "بال‌انگشتی‌های_کرتاسه_پسین_اروپا", "id": 5504781}, {"name": "خزندگان_کرتاسه_پسین_آمریکای_جنوبی", "id": 3619178}]}