{"name": "انواع_اسکی", "id": 4362800, "predecessors": [{"name": "اسکی", "id": 301561}, {"name": "آئین‌نامه‌ها_و_قوانین_ورزشی", "id": 1678266}], "successors": [{"name": "اسکی_آلپاین", "id": 1311052}, {"name": "اسکی_صحرانوردی", "id": 1311057}, {"name": "مدال‌آوران_المپیک_در_اسکی_پرش", "id": 2440902}, {"name": "اسکی‌بازان_پرش_اهل_اتریش", "id": 2441069}, {"name": "اسکی‌بازان_مرد_اسکی_صحرانوردی", "id": 2796828}, {"name": "ورزشکاران_دوگانه_مرد_اهل_آلمان", "id": 4379910}, {"name": "ورزشکاران_دوگانه_مرد_اهل_شوروی", "id": 4557815}, {"name": "ورزشکاران_دوگانه_مرد_اهل_نروژ", "id": 4557872}, {"name": "ورزشکاران_دوگانه_مرد_اهل_فنلاند", "id": 4600930}, {"name": "ورزشکاران_دوگانه_مرد_اهل_فرانسه", "id": 4905077}, {"name": "ورزشکاران_دوگانه_مرد_اهل_سوئد", "id": 5007355}, {"name": "ورزشکاران_دوگانه_مرد_اهل_روسیه", "id": 5007359}, {"name": "ورزشکاران_دوگانه_مرد_اهل_استونی", "id": 5086075}, {"name": "ورزشکاران_دوگانه_مرد_اهل_اوکراین", "id": 5304720}, {"name": "اسکی‌بازان_نوردیک_ترکیبی_مرد_اهل_آلمان", "id": 4379892}, {"name": "اسکی‌بازان_نوردیک_ترکیبی_مرد_اهل_فنلاند", "id": 4600933}, {"name": "اسکی‌بازان_نوردیک_ترکیبی_مرد_اهل_نروژ", "id": 4615912}, {"name": "اسکی‌بازان_نوردیک_ترکیبی_مرد_اهل_ژاپن", "id": 4619620}, {"name": "اسکی‌بازان_نوردیک_ترکیبی_مرد_اهل_اتریش", "id": 4649555}, {"name": "اسکی‌بازان_نوردیک_ترکیبی_مرد_اهل_استونی", "id": 5729378}, {"name": "اسکی‌بازان_پرش_مرد_اهل_آلمان", "id": 4379877}, {"name": "اسکی‌بازان_پرش_مرد_اهل_فنلاند", "id": 4600924}, {"name": "اسکی‌بازان_پرش_مرد_اهل_اسلوونی", "id": 4611543}, {"name": "اسکی‌بازان_پرش_مرد_اهل_ژاپن", "id": 4620131}, {"name": "اسکی‌بازان_پرش_مرد_اهل_لهستان", "id": 4624288}, {"name": "اسکی‌بازان_پرش_مرد_اهل_اتریش", "id": 4649545}, {"name": "اسکی‌بازان_پرش_مرد_اهل_فرانسه", "id": 5254658}, {"name": "اسکی‌بازان_پرش_مرد_اهل_چکسلواکی", "id": 5270181}, {"name": "اسکی‌بازان_پرش_مرد_اهل_نروژ", "id": 5289674}, {"name": "اسکی‌بازان_پرش_مرد_اهل_سوئد", "id": 5291792}, {"name": "اسکی‌بازان_پرش_مرد_اهل_استونی", "id": 5729377}, {"name": "اسکی‌بازان_نمایشی_مرد_اهل_ایالات_متحده_آمریکا", "id": 4690554}, {"name": "اسکی‌بازان_نمایشی_مرد_اهل_فرانسه", "id": 5244159}]}