{"name": "آرژانتینی‌های_مهاجرت‌کرده", "id": 4600727, "predecessors": [{"name": "افراد", "id": 112317}, {"name": "اهالی_آرژانتین", "id": 116229}, {"name": "افراد_بر_پایه_قومیت", "id": 331149}], "successors": [{"name": "آرژانتینی‌های_مهاجرت‌کرده_به_ایالات_متحده_آمریکا", "id": 3644650}, {"name": "آرژانتینی‌های_مهاجرت‌کرده_به_ایتالیا", "id": 3808409}, {"name": "آرژانتینی‌های_مهاجرت‌کرده_به_مکزیک", "id": 3808420}, {"name": "آرژانتینی‌های_مهاجرت‌کرده_به_اسپانیا", "id": 3808474}, {"name": "آرژانتینی‌های_مهاجرت‌کرده_به_پاراگوئه", "id": 4600716}, {"name": "آرژانتینی‌های_مهاجرت‌کرده_به_اسرائیل", "id": 4600717}, {"name": "آرژانتینی‌های_مهاجرت‌کرده_به_آلمان", "id": 4600718}, {"name": "آرژانتینی‌های_مهاجرت‌کرده_به_فرانسه", "id": 4600719}, {"name": "آرژانتینی‌های_مهاجرت‌کرده_به_اکوادور", "id": 4600721}, {"name": "آرژانتینی‌های_مهاجرت‌کرده_به_کلمبیا", "id": 4600722}, {"name": "آرژانتینی‌های_مهاجرت‌کرده_به_شیلی", "id": 4600723}, {"name": "آرژانتینی‌های_مهاجرت‌کرده_به_کانادا", "id": 4600724}, {"name": "آرژانتینی‌های_مهاجرت‌کرده_به_برزیل", "id": 4600725}, {"name": "آرژانتینی‌های_مهاجرت‌کرده_به_استرالیا", "id": 4600726}]}