{"name": "!Revalidações", "id": 2805525, "predecessors": [{"name": "!Avaliações_de_destaque", "id": 2935524}], "successors": [{"name": "!Revalidações_que_resultaram_na_remoção_do_destaque", "id": 2805527}, {"name": "!Revalidações_que_resultaram_na_manutenção_do_destaque", "id": 2805531}, {"name": "!Revalidações_que_resultaram_na_desqualificação_a_bom", "id": 2805532}, {"name": "!Revalidações_que_resultaram_na_manutenção_da_classificação_de_bom", "id": 2971030}, {"name": "!Revalidações_que_resultaram_na_remoção_da_classificação_de_bom", "id": 3702642}]}