{"name": "Teologia", "id": 40548, "predecessors": [{"name": "Crenças,_tradições_e_movimentos_religiosos", "id": 4355182}], "successors": [{"name": "Teólogos", "id": 14412}, {"name": "Direito_canônico", "id": 203468}, {"name": "Educação_religiosa", "id": 338643}, {"name": "Heresias", "id": 365919}, {"name": "Seminários", "id": 1122388}, {"name": "Livros_de_teologia", "id": 1448063}, {"name": "Concepções_de_Deus", "id": 1925441}, {"name": "Doutrina_e_teologia_da_Igreja_Católica", "id": 2134418}, {"name": "Correntes_e_movimentos_teológicos", "id": 2140418}, {"name": "Catecismos", "id": 2229459}, {"name": "Teologia_cristã", "id": 2679375}, {"name": "Teologia_judaica", "id": 3195108}, {"name": "Teologia_islâmica", "id": 3195173}, {"name": "Argumentos_contra_a_existência_de_Deus", "id": 3621350}, {"name": "Disciplinas_da_teologia", "id": 3839715}, {"name": "Não-teísmo", "id": 3860561}, {"name": "Teologia_feminista", "id": 3956816}, {"name": "Tradicionalismo", "id": 4410816}, {"name": "Revistas_de_teologia", "id": 5196744}, {"name": "Escotismo_(escolástica)", "id": 6428071}, {"name": "!Predefinições_sobre_teologia", "id": 7209903}, {"name": "Deísmo", "id": 1774774}, {"name": "Deus_(monoteísmo)", "id": 1918535}, {"name": "Religiões_monoteístas", "id": 3490046}]}