{"name": "Kapuloan_sa_Mosambik", "id": 5777971, "predecessors": [{"name": "Mga_pulo", "id": 44928}, {"name": "Heyograpiya", "id": 35111}], "successors": [{"name": "Kapuloan_sa_Nampula_(lalawigan)", "id": 5777965}, {"name": "Kapuloan_sa_Niassa_Province", "id": 5777998}, {"name": "Kapuloan_sa_Maputo_Province", "id": 5778099}, {"name": "Kapuloan_sa_Mosambik_nga_mas_dako_pa_kay_sa_1_ka_mga_kilometro_kwadrado", "id": 5778102}, {"name": "Kapuloan_sa_Cabo_Delgado_Province", "id": 5778139}, {"name": "Kapuloan_sa_Sofala_Province", "id": 5778197}, {"name": "Kapuloan_sa_Província_de_Zambézia", "id": 5778387}, {"name": "Kapuloan_sa_Inhambane_Province", "id": 5778632}, {"name": "Kapuloan_sa_Tete_(lalawigan)", "id": 5779402}]}