{"name": "أشخاص_من_نيوهامشير", "id": 1764265, "predecessors": [{"name": "نيوهامشير", "id": 1259334}, {"name": "أشخاص_من_آيوا", "id": 1925355}], "successors": [{"name": "مجرمون_من_نيوهامشير", "id": 3983686}, {"name": "شخصيات_مثلية_من_نيوهامشير", "id": 5225238}, {"name": "أشخاص_من_هانوفر_(نيوهامشير)", "id": 2180545}, {"name": "أشخاص_من_مقاطعة_غرافتون_(نيوهامشير)", "id": 2180550}, {"name": "أشخاص_من_مقاطعة_كوس_(نيوهامشير)", "id": 3973406}, {"name": "أشخاص_من_مقاطعة_كارول_(نيوهامشير)", "id": 3976797}, {"name": "أشخاص_من_مقاطعة_ميريماك_(نيوهامشير)", "id": 3977735}, {"name": "أشخاص_من_مقاطعة_هيلزبورو_(نيوهامشير)", "id": 3979188}, {"name": "أشخاص_من_مقاطعة_شيشاير_(نيوهامشير)", "id": 3979204}, {"name": "كتاب_من_نيوهامشير", "id": 2180628}, {"name": "رياضيون_من_نيوهامشير", "id": 3932259}, {"name": "مربون_من_نيوهامشير", "id": 3983683}, {"name": "ناشطون_من_نيوهامشير", "id": 3983691}, {"name": "قادة_دينيون_من_نيوهامشير", "id": 4119941}, {"name": "أطباء_من_نيوهامشير", "id": 4150566}, {"name": "أصحاب_أعمال_من_نيوهامشير", "id": 4154371}, {"name": "معماريون_من_نيوهامشير", "id": 4155932}, {"name": "أفراد_عسكريون_من_نيوهامشير", "id": 5328405}, {"name": "مخرجو_أفلام_من_نيوهامشير", "id": 5482372}, {"name": "فلاسفة_من_نيوهامشير", "id": 5653148}, {"name": "فنانون_من_نيوهامشير", "id": 5656207}, {"name": "محامون_من_ولاية_نيوهامشير", "id": 7155646}, {"name": "مخترعون_من_نيوهامشير", "id": 9036875}, {"name": "حكام_ولاية_نيوهامشير", "id": 808855}, {"name": "ديمقراطيون_من_ولاية_نيو_هامبشير", "id": 3394821}, {"name": "سياسيون_من_بورتسموث_(نيوهامشير)", "id": 4038848}, {"name": "سياسيون_من_مانشستر_(نيوهامبشير)", "id": 4162090}, {"name": "سياسيون_من_كونكورد_(نيوهامبشير)", "id": 4162541}, {"name": "أشخاص_من_بوسطن_الكبرى", "id": 3243830}, {"name": "أشخاص_من_دوفر_(نيوهامشير)", "id": 3681570}, {"name": "أشخاص_من_مانشستر_(نيوهامبشير)", "id": 3682813}, {"name": "أشخاص_من_كونكورد_(نيوهامبشير)", "id": 3685976}, {"name": "أشخاص_من_بورتسموث_(نيوهامشير)", "id": 3686300}, {"name": "أشخاص_من_لاكونيا_(نيوهامشير)", "id": 3699806}, {"name": "أشخاص_من_فرانكلين_(نيوهامشير)", "id": 3700576}, {"name": "أشخاص_من_روتشستر_(نيوهامشير)", "id": 3704747}, {"name": "أشخاص_من_لبنان_(نيوهامشير)", "id": 3705606}, {"name": "أشخاص_من_ناشوا_(نيو_هامبشير)", "id": 3706365}, {"name": "أشخاص_من_كين_(نيوهامشير)", "id": 3723284}, {"name": "أشخاص_من_كليرمونت_(نيوهامشير)", "id": 3731595}, {"name": "أشخاص_من_دورهام_(نيوهامشير)", "id": 3732578}, {"name": "أشخاص_من_تشيسترفيلد_(نيوهامشير)", "id": 3733298}, {"name": "أشخاص_من_ميريماك_(نيوهامشير)", "id": 4012881}, {"name": "أشخاص_من_برلين_(نيوهامشير)", "id": 5657794}, {"name": "أشخاص_من_هيلسبورو_(نيوهامشير)", "id": 3685971}, {"name": "أشخاص_من_لانكاستر_(نيوهامشير)", "id": 3692389}, {"name": "أشخاص_من_كوليبروك_(نيوهامشير)", "id": 3697985}, {"name": "أشخاص_من_ليتلتون_(نيوهامشير)", "id": 3709601}, {"name": "أشخاص_من_هامبتون_(نيوهامشير)", "id": 3711313}, {"name": "أشخاص_من_إيكستر", "id": 3712252}, {"name": "أشخاص_من_دوبلين_(نيوهامشير)", "id": 3712745}, {"name": "أشخاص_من_إينفيلد_(نيوهامشير)", "id": 3713678}, {"name": "أشخاص_من_كورنيش_(نيوهامشير)", "id": 3715447}, {"name": "أشخاص_من_تشارلستاون_(نيوهامشير)", "id": 3715488}, {"name": "أشخاص_من_هوليس_(نيوهامشير)", "id": 3715592}, {"name": "أشخاص_من_غيلمانتون_(نيوهامشير)", "id": 3722536}, {"name": "أشخاص_من_هامبتون_فالس_(نيوهامشير)", "id": 3722766}, {"name": "أشخاص_من_فارمينغتون_(نيوهامشير)", "id": 3723671}, {"name": "أشخاص_من_لايم_(نيوهامشير)", "id": 3728393}, {"name": "أشخاص_من_جافري_(نيوهامشير)", "id": 3731908}, {"name": "أشخاص_من_كانتربوري_(نيوهامشير)", "id": 3732585}, {"name": "أشخاص_من_فيتزويليام_(نيوهامشير)", "id": 3732933}, {"name": "أشخاص_من_نيو_إيبسويتش_(نيوهامشير)", "id": 4012854}, {"name": "أشخاص_من_لندندري_(نيوهامشير)", "id": 4074745}, {"name": "أشخاص_من_غوفستاون_(نيوهامشير)", "id": 4094178}, {"name": "أشخاص_من_هوبكينتون_(نيوهامشير)", "id": 4150327}, {"name": "أشخاص_من_هوكسيت_(نيوهامشير)", "id": 4152727}, {"name": "أشخاص_من_نيو_هامبتون_(نيوهامشير)", "id": 4187001}, {"name": "أشخاص_من_ديري_(نيوهامشير)", "id": 4205725}, {"name": "أشخاص_من_فرانسيستاون_(نيوهامشير)", "id": 4293198}, {"name": "أشخاص_من_بيتربورو_(نيوهامشير)", "id": 4750406}, {"name": "أشخاص_من_فرانكونيا_(نيوهامشير)", "id": 4816653}, {"name": "أشخاص_من_نيوبورت_(نيوهامشير)", "id": 5304633}, {"name": "أشخاص_من_نيو_لندن_(نيوهامشير)", "id": 5484001}, {"name": "أشخاص_من_كونواي_(نيوهامشير)", "id": 5485528}, {"name": "أشخاص_من_ديرفيلد_(نيوهامشير)", "id": 5487537}, {"name": "أشخاص_من_أوسيبي_(نيوهامشير)", "id": 5487715}, {"name": "أشخاص_من_مونت_فيرنون_(نيوهامشير)", "id": 5489514}, {"name": "أشخاص_من_بيمبروك_(نيوهامشير)", "id": 5509432}, {"name": "أشخاص_من_هينسديل_(نيوهامشير)", "id": 5650956}, {"name": "أشخاص_من_نيلسون_(نيوهامشير)", "id": 5652183}, {"name": "أشخاص_من_هافرهيل_(نيوهامشير)", "id": 5652926}, {"name": "أشخاص_من_تشيستر_(نيوهامشير)", "id": 5652947}, {"name": "أشخاص_من_هانكوك_(نيوهامشير)", "id": 5655978}, {"name": "أشخاص_من_نيوماركت_(نيوهامشير)", "id": 5656819}, {"name": "أشخاص_من_غيلفورد_(نيوهامشير)", "id": 5657149}, {"name": "أشخاص_من_ميرديث_(نيوهامشير)", "id": 5657937}, {"name": "أشخاص_من_كانديا_(نيوهامشير)", "id": 6091238}, {"name": "أشخاص_من_ولبوول", "id": 7305223}, {"name": "أشخاص_من_كانان_(نيوهامشير)", "id": 7596609}, {"name": "أشخاص_من_ماسون_(نيوهامشير)", "id": 7602467}, {"name": "أشخاص_من_دونبارتون_(نيوهامشير)", "id": 7603696}, {"name": "أشخاص_من_لانداف_(نيوهامشير)", "id": 7605343}, {"name": "أشخاص_من_نيو_بوسطن", "id": 7606552}, {"name": "موسيقيون_من_نيوهامشير", "id": 3960304}, {"name": "كوميديون_من_نيوهامشير", "id": 4078056}, {"name": "ممثلات_من_نيو_هامبشير", "id": 2000014}, {"name": "ممثلون_من_ولاية_نيو_هامبشاير", "id": 2360241}, {"name": "ممثلون_من_مانشستر_(نيوهامبشير)", "id": 4062688}, {"name": "أشخاص_من_نيوهامشير_في_الحرب_الأهلية_الأمريكية", "id": 4139551}, {"name": "عمدات_مانشستر_(نيوهامبشير)", "id": 4162089}, {"name": "عمدات_بورتسموث_(نيوهامشير)", "id": 4169334}, {"name": "خريجو_أكاديمية_فيلبس_إيكستر", "id": 7455657}, {"name": "سياسيون_من_ناشوا_(نيوهامشير)", "id": 5626306}]}