{"name": "بوابات_أديان", "id": 2105856, "predecessors": [{"name": "دين", "id": 436567}, {"name": "محتويات_ويكيبيديا", "id": 246386}], "successors": [{"name": "بوابة_مسيحية", "id": 1971474}, {"name": "بوابة_بهائية", "id": 1990062}, {"name": "بوابة_سيخية", "id": 2076434}, {"name": "بوابة_أديان", "id": 2105855}, {"name": "بوابة_زرادشتية", "id": 2106484}, {"name": "بوابة_اليهودية", "id": 2163881}, {"name": "بوابة_الإسلام", "id": 2218579}, {"name": "بوابة_بوذية", "id": 2466005}, {"name": "بوابة_تصوف", "id": 2470789}, {"name": "بوابة_هندوسية", "id": 2522490}, {"name": "بوابة_الإنجيل", "id": 2540894}, {"name": "بوابة_العالم_الإسلامي", "id": 2881149}, {"name": "بوابة_إلحاد", "id": 2881236}, {"name": "بوابة_الخلافة_الراشدة", "id": 2424858}, {"name": "بوابة_سمرقند", "id": 2948240}, {"name": "بوابة_فكر_إسلامي", "id": 3013634}, {"name": "بوابة_القرآن", "id": 3862863}]}