{"name": "لسانيات", "id": 226594, "predecessors": [{"name": "إنسانيات", "id": 20011}, {"name": "اتصالات", "id": 43976}, {"name": "علم_الإنسان", "id": 20029}, {"name": "علوم_استعرافية", "id": 189718}, {"name": "علوم_شكلية", "id": 356832}, {"name": "لغة", "id": 224716}, {"name": "لغويون", "id": 15625}], "successors": [{"name": "لغات", "id": 4780}, {"name": "مصطلحات", "id": 10681}, {"name": "لغويون", "id": 15625}, {"name": "نحو", "id": 17369}, {"name": "بنيوية", "id": 23564}, {"name": "فلسفة_اللغة", "id": 26424}, {"name": "كتابة", "id": 30013}, {"name": "اتصالات", "id": 43976}, {"name": "مترجمون", "id": 179786}, {"name": "علوم_استعرافية", "id": 189718}, {"name": "قواعد_الكتابة", "id": 192986}, {"name": "لغة", "id": 224716}, {"name": "صرف", "id": 231534}, {"name": "لغات_اشتقاقية", "id": 288115}, {"name": "قراءة", "id": 480333}, {"name": "سياسة_اللغة", "id": 500335}, {"name": "وحدات_لغوية", "id": 514922}, {"name": "قواعد_اللغة", "id": 527839}, {"name": "لغويات_تاريخية", "id": 556172}, {"name": "نطقيات", "id": 610400}, {"name": "علم_الصوت", "id": 615157}, {"name": "قوائم_لغات", "id": 821639}, {"name": "تنميط_لغوي", "id": 841314}, {"name": "بلاغة", "id": 916408}, {"name": "لغات_مصطنعة", "id": 924688}, {"name": "علم_المعاني", "id": 946331}, {"name": "لغويات_عصبية", "id": 967534}, {"name": "صوغ_الألفاظ", "id": 996649}, {"name": "أنظمة_نسخ", "id": 1035947}, {"name": "علم_اللهجات", "id": 1051460}, {"name": "علم_المعاجم", "id": 1051464}, {"name": "لغويات_حاسوبية", "id": 1415415}, {"name": "لغويات_المجاميع", "id": 1415449}, {"name": "علم_العلامات", "id": 1425264}, {"name": "خوارزميات_البحث_الثنائي", "id": 1445991}, {"name": "لغويات_تطبيقية", "id": 1478600}, {"name": "لغويات_اجتماعية", "id": 1478601}, {"name": "تاريخ_علم_اللغة", "id": 1548645}, {"name": "تعابير_لغوية", "id": 1555339}, {"name": "تلاعب_بالألفاظ", "id": 1561386}, {"name": "علماء_لغات", "id": 1673579}, {"name": "علم_الصوتيات", "id": 1854501}, {"name": "فقه_اللغة", "id": 1854689}, {"name": "صناعة_معجمية", "id": 1863256}, {"name": "مصطلحات_لغوية", "id": 2205216}, {"name": "فرضيات_لغوية", "id": 2406141}, {"name": "خلافات_لغوية", "id": 2453493}, {"name": "علم_التسميات", "id": 2453504}, {"name": "تصنيف_اللغات", "id": 2708468}, {"name": "قوائم_لغوية", "id": 2970768}, {"name": "اللغويات_المعرفية", "id": 2995434}, {"name": "جغرافيا_لغوية", "id": 2996976}, {"name": "مؤسسات_لسانية", "id": 2998874}, {"name": "تحليل_الخطاب", "id": 3057652}, {"name": "شرطيات", "id": 3096900}, {"name": "نظرية_الاتصال", "id": 3111220}, {"name": "شكلتة", "id": 3303793}, {"name": "لسانيات_اللغة_العربية", "id": 3528205}, {"name": "دراسات_ترجمة", "id": 3589044}, {"name": "لسانيات_أنثروبولوجية", "id": 4012954}, {"name": "علم_اللغة_النفسي", "id": 4019335}, {"name": "اتصال_لغوي", "id": 4021632}, {"name": "تداوليات", "id": 4024519}, {"name": "مصطلحات_لغويات", "id": 4164997}, {"name": "ألعاب_الكلمات", "id": 4620598}, {"name": "لسانيات_زائفة", "id": 7445156}, {"name": "فلاسفة_من_لغويات", "id": 8214191}, {"name": "فروع_اللسانيات", "id": 9396398}, {"name": "نقد_نصي", "id": 363323}, {"name": "باليوغرافيا", "id": 421513}, {"name": "قواميس", "id": 181558}, {"name": "مجلات_علمية_لغوية", "id": 3527942}, {"name": "كتب_لغوية", "id": 4147145}, {"name": "أعمال_عن_فقه_اللغة", "id": 7760652}, {"name": "معجمات_عربية", "id": 229380}, {"name": "قواميس_إنجليزية", "id": 1718335}, {"name": "قواميس_فارسية", "id": 2075864}, {"name": "قواميس_فرنسية", "id": 3547581}, {"name": "قواميس_تركية", "id": 4043295}, {"name": "قواميس_ألمانية", "id": 4113130}, {"name": "أفلام_عن_اللغة_والترجمة", "id": 2002353}, {"name": "مجلات_ترجمة_أدبية", "id": 3213713}]}