{"name": "اقتصاد", "id": 3063744, "predecessors": [{"name": "مجتمع", "id": 8164}], "successors": [{"name": "مال", "id": 22628}, {"name": "عمل", "id": 133650}, {"name": "بنية_تحتية", "id": 192168}, {"name": "أنظمة_اقتصادية", "id": 267998}, {"name": "المثلية_والاقتصاد", "id": 1807248}, {"name": "تنمية_اقتصادية", "id": 2552610}, {"name": "قطاعات_اقتصادية", "id": 2708621}, {"name": "مهن_تجارية", "id": 2006539}, {"name": "استشارات_إدارية", "id": 4029332}, {"name": "قوائم_اقتصادية", "id": 270651}, {"name": "قوائم_وسائل_نقل", "id": 540666}, {"name": "قوائم_ذات_صلة_بالسياحة", "id": 2426773}, {"name": "قوائم_أعمال", "id": 2760600}, {"name": "قوائم_متعلقة_بالطاقة", "id": 2778399}, {"name": "قوائم_متعلقة_بالاتصال", "id": 2970770}, {"name": "قوائم_متعلقة_بالضرائب", "id": 4027414}, {"name": "قوائم_متعلقة_بزراعة", "id": 4028725}, {"name": "مهن_تمويل", "id": 7813081}, {"name": "صناعة_النسيج", "id": 41888}, {"name": "صناعة_طيران", "id": 99351}, {"name": "صناعات_غذائية", "id": 101734}, {"name": "صناعات_الخدمات", "id": 275861}, {"name": "صناعة_عسكرية", "id": 420471}, {"name": "صناعة_اللدائن", "id": 1043014}, {"name": "صناعة_الفضاء", "id": 2907872}, {"name": "صناعة_المركبات", "id": 3046910}, {"name": "صناعة_علوم_الحياة", "id": 3070360}, {"name": "صناعات_ثقيلة", "id": 4012713}, {"name": "صناعة_طاقة", "id": 4107436}, {"name": "صناعة_المطاط", "id": 5472435}, {"name": "صناعة_الألماس", "id": 6368644}, {"name": "شركات_حوسبة", "id": 421807}, {"name": "صناعة_البرمجيات", "id": 970399}, {"name": "معارض_تجارية_متعلقة_بالحاسوب", "id": 1108475}, {"name": "برمجيات_وهمية", "id": 7569933}, {"name": "معماريون", "id": 12142}, {"name": "شركات_بناء_وأشغال_عامة", "id": 357091}, {"name": "مصطلحات_عمارة", "id": 576722}, {"name": "مهندسو_إنشاءات", "id": 589217}, {"name": "مهن_قطاع_الإنشاءات", "id": 1914452}, {"name": "أصحاب_أعمال_في_مجال_البناء", "id": 2006561}, {"name": "مهندسون_مدنيون", "id": 2094983}, {"name": "شركات_أسمنت", "id": 3255120}, {"name": "مصنعو_رافعات", "id": 7365258}, {"name": "مهن_بناء_واستخلاص", "id": 7423261}, {"name": "شركات_السكك_الحديدية", "id": 6652063}, {"name": "شركات_عقارات", "id": 673819}, {"name": "أصحاب_أعمال_في_مجال_العقارات", "id": 2006559}, {"name": "الطاقة_النووية_حسب_البلد", "id": 2713528}, {"name": "شركات_طلاء", "id": 2643478}, {"name": "مصممو_مجوهرات_أمريكيون", "id": 1124795}, {"name": "شركات_ألعاب", "id": 426996}, {"name": "مخترعو_ألعاب", "id": 4660959}, {"name": "زراعة", "id": 8108}, {"name": "تعدين", "id": 479025}, {"name": "علم_التحريج", "id": 561173}, {"name": "غاز_طبيعي", "id": 615131}, {"name": "صناعة_سمكية", "id": 1270401}, {"name": "صناعة_النفط", "id": 1704206}, {"name": "تجارة_الفراء", "id": 2391773}, {"name": "مواش", "id": 3273357}, {"name": "صناعة_الأخشاب", "id": 3581020}, {"name": "صناعة_الجلود", "id": 8857762}, {"name": "تعدين_الفحم", "id": 2759704}, {"name": "شبكات_تلفزيونية", "id": 349764}, {"name": "قنوات_مدفوعة", "id": 3009356}]}