{"name": "العلم_في_2017", "id": 3391148, "predecessors": [{"name": "2017", "id": 188851}, {"name": "العلم_في_عقد_2010", "id": 1721481}, {"name": "تاريخ_العلوم", "id": 25828}], "successors": [{"name": "زلازل_2017", "id": 3440671}, {"name": "أجرام_فلكية_اكتشفت_في_2017", "id": 3472881}, {"name": "الفضاء_في_2017", "id": 3520097}, {"name": "رحلات_الفضاء_في_2017", "id": 3520300}, {"name": "أجرام_قريبة_من_الأرض_في_2017", "id": 3568357}, {"name": "علم_الحاسوب_في_2017", "id": 4120655}, {"name": "تصنيف_أحفوري_وصف_في_2017", "id": 5489466}, {"name": "أصنوفات_أحفورية_وصفت_في_2017", "id": 5898308}, {"name": "كوارث_صحية_في_2017", "id": 4168186}, {"name": "بكتيريا_وصفت_في_2017", "id": 5225579}]}