{"name": "أماكن_مأهولة_في_إقليم_سطات", "id": 3468267, "predecessors": [{"name": "أماكن_مأهولة_في_المغرب", "id": 1501568}, {"name": "جغرافيا_المغرب", "id": 54910}], "successors": [{"name": "أماكن_مأهولة_في_أولاد_امحمد_(إقليم_سطات)", "id": 3474619}, {"name": "أماكن_مأهولة_في_رأس_العين_الشاوية", "id": 3474620}, {"name": "أماكن_مأهولة_في_سيدي_حجاج", "id": 3474624}, {"name": "أماكن_مأهولة_في_لحوازة", "id": 3474661}, {"name": "أماكن_مأهولة_في_امزورة", "id": 3474663}, {"name": "أماكن_مأهولة_في_أولاد_سعيد_(إقليم_سطات)", "id": 3474665}, {"name": "أماكن_مأهولة_في_سيدي_العايدي", "id": 3474668}, {"name": "أماكن_مأهولة_في_عين_الضربان_(عين_الضربان_لحلاف)", "id": 3481799}, {"name": "أماكن_مأهولة_في_حمداوة_الجنوبية_(عين_الضربان_لحلاف)", "id": 3481800}, {"name": "أماكن_مأهولة_في_أولاد_زهرة_(بوڭرڭوح)", "id": 3481801}, {"name": "أماكن_مأهولة_في_بني_ريتون_(بوڭرڭوح)", "id": 3481802}, {"name": "أماكن_مأهولة_في_لحلاف_(لحلاف_مزاب)", "id": 3481804}, {"name": "أماكن_مأهولة_في_العين_البيضاء_الفرش_(الخزازرة)", "id": 3481806}, {"name": "أماكن_مأهولة_في_عين_الرباح_(الخزازرة)", "id": 3481807}, {"name": "أماكن_مأهولة_في_قصبة_ولد_حادة_(الخزازرة)", "id": 3481808}, {"name": "أماكن_مأهولة_في_السوالم_(امنيع)", "id": 3481810}, {"name": "أماكن_مأهولة_في_اجموحة_(امنيع)", "id": 3481812}, {"name": "أماكن_مأهولة_في_امريزيك_(امريزيڭ)", "id": 3481813}, {"name": "أماكن_مأهولة_في_بني_سنجاج_(امريزيڭ)", "id": 3481814}, {"name": "أماكن_مأهولة_في_ليسوف_(امريزيڭ)", "id": 3481815}, {"name": "أماكن_مأهولة_في_المعاريف_(إمكارطو)", "id": 3481817}, {"name": "أماكن_مأهولة_في_أولاد_عبد_الله_(إمكارطو)", "id": 3481818}, {"name": "أماكن_مأهولة_في_أولاد_احمامة_(إمكارطو)", "id": 3481819}, {"name": "أماكن_مأهولة_في_أولاد_عبادي_(انخيلة)", "id": 3481820}, {"name": "أماكن_مأهولة_في_لمخلخليين_(انخيلة)", "id": 3481822}, {"name": "أماكن_مأهولة_في_بني_ايدو_(واد_النعناع)", "id": 3481823}, {"name": "أماكن_مأهولة_في_وادي_النعناع_(واد_النعناع)", "id": 3481824}, {"name": "أماكن_مأهولة_في_أولاد_اشبانة_(أولاد_شبانة)", "id": 3481826}, {"name": "أماكن_مأهولة_في_أولاد_موسى_(أولاد_فارس)", "id": 3481828}, {"name": "أماكن_مأهولة_في_أولاد_عدو_(أولاد_فارس)", "id": 3481829}, {"name": "أماكن_مأهولة_في_أولاد_سيدي_بلكاسم_(السڭامنة)", "id": 3481842}, {"name": "أماكن_مأهولة_في_أولاد_اعمر_(سيدي_عبد_الكريم)", "id": 3481844}, {"name": "أماكن_مأهولة_في_حمداوة1_(سيدي_عبد_الكريم)", "id": 3481846}, {"name": "أماكن_مأهولة_في_أولاد_بن_اعريف_(سيدي_الذهبي)", "id": 3481847}, {"name": "أماكن_مأهولة_في_المعاريف_(سيدي_الذهبي)", "id": 3481848}, {"name": "أماكن_مأهولة_في_عين_ابلال_(عين_بلال)", "id": 3481882}, {"name": "أماكن_مأهولة_في_بني_اخلوك_(بني_خلوڭ)", "id": 3481884}, {"name": "أماكن_مأهولة_في_الخناسنة_(دار_الشافعي)", "id": 3481886}, {"name": "أماكن_مأهولة_في_أولاد_العكارية_(دار_الشافعي)", "id": 3481887}, {"name": "أماكن_مأهولة_في_القراقرة_(لقراقرة)", "id": 3481888}, {"name": "أماكن_مأهولة_في_مسكورة_(مسكورة)", "id": 3481889}, {"name": "أماكن_مأهولة_في_أولاد_عامر_(أولاد_عامر)", "id": 3481890}, {"name": "أماكن_مأهولة_في_أولاد_بوعلي_(أولاد_بوعلي_النواجة)", "id": 3483603}, {"name": "أماكن_مأهولة_في_أولاد_فارس_(أولاد_فارس_الحلة)", "id": 3481892}, {"name": "أماكن_مأهولة_في_ليساسفة_(أولاد_فريحة)", "id": 3481893}, {"name": "أماكن_مأهولة_في_أهل_الغابة_(أولاد_فريحة)", "id": 3481894}, {"name": "أماكن_مأهولة_في_أولاد_سيدي_يحيى_بن_ايعيش_(سيدي_أحمد_الخدير)", "id": 3481895}, {"name": "أماكن_مأهولة_في_الخشاشنة_(سيدي_بومهدي)", "id": 3481898}, {"name": "أماكن_مأهولة_في_العراعير_(عين_نزاغ)", "id": 3481914}, {"name": "أماكن_مأهولة_في_أولاد_عروس1_(عين_نزاغ)", "id": 3481915}, {"name": "أماكن_مأهولة_في_أولاد_عروس2_(عين_نزاغ)", "id": 3481916}, {"name": "أماكن_مأهولة_في_بني_يكرين_(بني_ياڭرين)", "id": 3481917}, {"name": "أماكن_مأهولة_في_شرقاوة_(كدانة)", "id": 3481919}, {"name": "أماكن_مأهولة_في_بني_امحمد_(كدانة)", "id": 3481921}, {"name": "أماكن_مأهولة_في_الزراهنة_(كدانة)", "id": 3481922}, {"name": "أماكن_مأهولة_في_أولاد_الزقاق_(كيسر)", "id": 3481923}, {"name": "أماكن_مأهولة_في_الحمادات_(كيسر)", "id": 3481924}, {"name": "أماكن_مأهولة_في_أولاد_اجميل_(اخميسات_الشاوية)", "id": 3481926}, {"name": "أماكن_مأهولة_في_أولاد_عيسى_(اخميسات_الشاوية)", "id": 3481927}, {"name": "أماكن_مأهولة_في_أولاد_امحمد_(مشرع_بن_عبو)", "id": 3481933}, {"name": "أماكن_مأهولة_في_المشرع_(مشرع_بن_عبو)", "id": 3481934}, {"name": "أماكن_مأهولة_في_أولاد_عفيف_(أولاد_عفيف)", "id": 3481940}, {"name": "أماكن_مأهولة_في_أولاد_الصغير_(أولاد_الصغير)", "id": 3481946}, {"name": "أماكن_مأهولة_في_أولاد_المامون_(ريمة)", "id": 3481947}, {"name": "أماكن_مأهولة_في_أولاد_الخادم_(ريمة)", "id": 3481949}, {"name": "أماكن_مأهولة_في_أولاد_يوسف_(سيدي_محمد_بن_رحال)", "id": 3481955}, {"name": "أماكن_مأهولة_في_المركز_(سيدي_محمد_بن_رحال)", "id": 3481956}, {"name": "أماكن_مأهولة_في_أولاد_امحمد_(سيدي_محمد_بن_رحال)", "id": 3481957}, {"name": "أماكن_مأهولة_في_مالين_الواد_1_(تامدروست)", "id": 3481958}, {"name": "أماكن_مأهولة_في_مالين_الواد_2_(تامدروست)", "id": 3481960}, {"name": "أماكن_مأهولة_في_التوالت_(الثوالث)", "id": 3481961}, {"name": "أماكن_مأهولة_في_مليتة_(الثوالث)", "id": 3481962}]}