{"name": "العلاقات_البرازيلية_الأمريكية", "id": 5849079, "predecessors": [{"name": "علاقات_البرازيل_الثنائية", "id": 1985945}, {"name": "علاقات_الولايات_المتحدة_الأمريكية_وأمريكا_الجنوبية", "id": 2739822}], "successors": [{"name": "أمريكيون_من_أصل_برازيلي", "id": 1472678}, {"name": "مغتربون_برازيليون_في_الولايات_المتحدة", "id": 2552347}, {"name": "أمريكيون_مغتربون_في_البرازيل", "id": 3921768}, {"name": "برازيليون_من_أصل_أمريكي", "id": 3921773}, {"name": "سفراء_الولايات_المتحدة_لدى_البرازيل", "id": 4101350}, {"name": "سفراء_البرازيل_لدى_الولايات_المتحدة", "id": 4112231}, {"name": "العلاقات_الأمريكية_البرازيلية_العسكرية", "id": 8412316}]}