{"name": "Česká_opera", "id": 765708, "predecessors": [{"name": "Česká_hudba", "id": 4432}, {"name": "České_divadlo", "id": 14556}, {"name": "Opera", "id": 243503}], "successors": [{"name": "Čeští_libretisté", "id": 27430}, {"name": "Opery_Bohuslava_Martinů", "id": 588121}, {"name": "Opery_Bedřicha_Smetany", "id": 588127}, {"name": "Opery_Antonína_Dvořáka", "id": 588215}, {"name": "Opery_Leoše_Janáčka", "id": 588218}, {"name": "Opery_Josefa_Myslivečka", "id": 588315}, {"name": "Opery_v_češtině", "id": 600217}, {"name": "Opery_Františka_Škroupa", "id": 669687}, {"name": "Opery_Zdeňka_Fibicha", "id": 688608}, {"name": "Opery_Josefa_Bohuslava_Foerstera", "id": 697809}, {"name": "Opery_Karla_Bendla", "id": 759221}, {"name": "Čeští_operní_pěvci", "id": 764673}, {"name": "Opery_Josefa_Richarda_Rozkošného", "id": 769770}, {"name": "Opery_Otmara_Máchy", "id": 959725}, {"name": "Opery_Ilji_Hurníka", "id": 975518}, {"name": "Čeští_umělci_působící_v_MET", "id": 1285147}, {"name": "Opery_Josefa_Bartovského", "id": 1331449}, {"name": "Čeští_operní_skladatelé", "id": 1444409}, {"name": "Čeští_operní_režiséři", "id": 1456089}, {"name": "Operní_scény_v_Česku", "id": 1508393}, {"name": "Opery_Jiřího_Smutného", "id": 1800326}, {"name": "Opery_a_melodramy_Františka_Ondřeje_Holého", "id": 1897268}, {"name": "Opery_Floriana_Leopolda_Gassmanna", "id": 1910279}, {"name": "Opery_poprvé_uvedené_v_Praze", "id": 1058674}, {"name": "Opery_poprvé_uvedené_v_Plzni", "id": 1058684}, {"name": "Opery_poprvé_uvedené_v_Olomouci", "id": 1058725}, {"name": "Opery_poprvé_uvedené_v_Brně", "id": 1058731}, {"name": "Opery_poprvé_uvedené_v_Českých_Budějovicích", "id": 1058858}, {"name": "Opery_poprvé_uvedené_v_Ostravě", "id": 1058863}]}