{"name": "Musique_en_Suisse", "id": 3978451, "predecessors": [{"name": "Art_en_Suisse", "id": 543855}, {"name": "Anthropologie", "id": 84938}], "successors": [{"name": "Groupe_musical_suisse", "id": 167934}, {"name": "Festival_de_musique_en_Suisse", "id": 339430}, {"name": "Salle_de_concert_en_Suisse", "id": 894178}, {"name": "Orchestre_suisse", "id": 1460664}, {"name": "Album_numéro_un_en_Suisse", "id": 4225120}, {"name": "Suisse_au_Concours_Eurovision_de_la_chanson", "id": 5518222}, {"name": "Musique_dans_le_canton_de_Genève", "id": 10259287}, {"name": "Ensemble_suisse_de_musique_classique", "id": 11773418}, {"name": "Single_numéro_un_en_Suisse", "id": 3978430}, {"name": "Album_enregistré_au_Mountain_Studios", "id": 8371126}, {"name": "Single_certifié_platine_en_Suisse", "id": 9272140}, {"name": "Single_certifié_or_en_Suisse", "id": 9686296}, {"name": "Single_certifié_double_platine_en_Suisse", "id": 11222715}, {"name": "Album_de_Yello", "id": 2920635}]}