{"name": "Bureau_exécutif_du_président_des_États-Unis", "id": 4191595, "predecessors": [{"name": "Branche_exécutive_du_gouvernement_des_États-Unis", "id": 4831550}, {"name": "Maison-Blanche", "id": 7086525}, {"name": "Présidence_des_États-Unis", "id": 4831506}], "successors": [{"name": "Porte-parole_de_la_Maison-Blanche", "id": 1146115}, {"name": "Conseiller_à_la_sécurité_nationale_(États-Unis)", "id": 1224237}, {"name": "Chef_de_cabinet_de_la_Maison-Blanche", "id": 3376635}, {"name": "Représentant_américain_au_commerce", "id": 10740249}, {"name": "Directeur_de_la_communication_de_la_Maison-Blanche", "id": 11527759}]}