{"name": "코파_아메리카", "id": 120806, "predecessors": [{"name": "CONMEBOL_주관_대회", "id": 125615}], "successors": [{"name": "코파_아메리카에_관한_둘러보기_틀", "id": 442116}, {"name": "코파_아메리카_결승전", "id": 1454561}, {"name": "코파_아메리카_센테나리오", "id": 1502809}, {"name": "코파_아메리카_심판", "id": 1986433}, {"name": "코파_아메리카_선수_명단", "id": 2525644}, {"name": "2019년_코파_아메리카", "id": 2525684}, {"name": "2021년_코파_아메리카", "id": 2525707}, {"name": "2011년_코파_아메리카_참가_선수", "id": 666559}, {"name": "2011년_코파_아메리카_참가_감독", "id": 1502832}, {"name": "1975년_코파_아메리카_참가_선수", "id": 1144718}, {"name": "1979년_코파_아메리카_참가_선수", "id": 1144721}, {"name": "1983년_코파_아메리카_참가_선수", "id": 1144722}, {"name": "1987년_코파_아메리카_참가_선수", "id": 1144723}, {"name": "1989년_코파_아메리카_참가_선수", "id": 1144724}, {"name": "1989년_코파_아메리카_참가_감독", "id": 1502822}, {"name": "1991년_코파_아메리카_참가_선수", "id": 1144725}, {"name": "1993년_코파_아메리카_참가_선수", "id": 1144726}, {"name": "1993년_코파_아메리카_참가_감독", "id": 1502825}, {"name": "1995년_코파_아메리카_참가_선수", "id": 1144727}, {"name": "1995년_코파_아메리카_참가_감독", "id": 1502826}, {"name": "1997년_코파_아메리카_참가_선수", "id": 1144728}, {"name": "1997년_코파_아메리카_참가_감독", "id": 1502827}, {"name": "1999년_코파_아메리카_참가_선수", "id": 985759}, {"name": "1999년_코파_아메리카_참가_감독", "id": 1502828}, {"name": "2001년_코파_아메리카_참가_선수", "id": 1144729}, {"name": "2001년_코파_아메리카_참가_감독", "id": 1502829}, {"name": "2004년_코파_아메리카_참가_선수", "id": 1144730}, {"name": "2004년_코파_아메리카_참가_감독", "id": 1502830}, {"name": "2015년_코파_아메리카_참가_선수", "id": 1311924}, {"name": "2015년_코파_아메리카_참가_감독", "id": 1502833}, {"name": "코파_아메리카_센테나리오_참가_감독", "id": 1502823}, {"name": "2007년_코파_아메리카_참가_감독", "id": 1502831}, {"name": "2019년_코파_아메리카_참가_감독", "id": 2525712}, {"name": "2021년_코파_아메리카_참가_감독", "id": 2997316}, {"name": "1923년_남미_축구_선수권_대회_참가_선수", "id": 3662995}, {"name": "1924년_남미_축구_선수권_대회_참가_선수", "id": 3662996}, {"name": "1925년_남미_축구_선수권_대회_참가_선수", "id": 3662997}, {"name": "1926년_남미_축구_선수권_대회_참가_선수", "id": 3662998}, {"name": "1927년_남미_축구_선수권_대회_참가_선수", "id": 3663000}, {"name": "1929년_남미_축구_선수권_대회_참가_선수", "id": 3663001}, {"name": "1935년_남미_축구_선수권_대회_참가_선수", "id": 3663002}, {"name": "1937년_남미_축구_선수권_대회_참가_선수", "id": 3663005}, {"name": "1942년_남미_축구_선수권_대회_참가_선수", "id": 3663007}, {"name": "1945년_남미_축구_선수권_대회_참가_선수", "id": 3663008}, {"name": "1946년_남미_축구_선수권_대회_참가_선수", "id": 3663009}, {"name": "1947년_남미_축구_선수권_대회_참가_선수", "id": 3663010}, {"name": "1949년_남미_축구_선수권_대회_참가_선수", "id": 3663011}, {"name": "1953년_남미_축구_선수권_대회_참가_선수", "id": 3663012}, {"name": "1956년_남미_축구_선수권_대회_참가_선수", "id": 3663014}, {"name": "1957년_남미_축구_선수권_대회_참가_선수", "id": 3663019}, {"name": "1959년_남미_축구_선수권_대회_(아르헨티나)_참가_선수", "id": 3663023}, {"name": "1967년_남미_축구_선수권_대회_참가_선수", "id": 3662999}]}